lab12/cnt_nonblk.v
module cnt_nonblk(clk, rst, a_in, b_in, a_out, b_out);

    input clk, rst, a_in, b_in;
    output a_out, b_out;
    reg a, b;

    assign a_out = a;
    assign b_out = b;

    always@(posedge clk or negedge rst)begin
        if(~rst) begin
            a <= a_in;
            b <= b_in;
        end
        else begin
           a <= b;
           b <= a; 
        end
    end

endmodule

lab12/cnt_blk.v
module cnt_blk(clk, rst, a_in, b_in, a_out, b_out);

    input clk, rst, a_in, b_in;
    output a_out, b_out;
    reg a, b;

    assign a_out = a;
    assign b_out = b;

    always@(posedge clk or negedge rst)begin
        if(~rst) begin
            a = a_in;
            b = b_in;
        end
        else begin
           a = b;
           b = a; 
        end
    end

endmodule

lab12/testbench.v
`timescale  100ms/1ms
module testbench();
	reg clk;
	reg rst_n;

	reg a_in, b_in;
	wire blk_a_out, blk_b_out;
	wire  non_blk_a_out, non_blk_b_out;

	cnt_blk blk1(clk, rst_n, a_in, b_in, blk_a_out, blk_b_out);
	cnt_nonblk nonblk1(clk, rst_n, a_in, b_in, non_blk_a_out, non_blk_b_out);
	localparam CLK_PERIOD = 10;
	always #(CLK_PERIOD/2) clk=~clk;

	initial begin
		$dumpfile("testbench.vcd");
		$dumpvars(0, testbench);
	end

	initial begin
		#1 rst_n<=1'bx;clk<=1'bx; a_in =1'bx; b_in = 1'bx;
		#(CLK_PERIOD*3) rst_n<=1;
		#(CLK_PERIOD*3) rst_n<=0;clk<=0;a_in = 0; b_in = 1;
		repeat(5) @(posedge clk);
		rst_n<=1;
		#(CLK_PERIOD*6)
		#(CLK_PERIOD/2) rst_n<=0;a_in = 1; b_in = 0;
		#(CLK_PERIOD/4) rst_n<=1;
		#(CLK_PERIOD*5) $finish;
	end

endmodule

lab12/testbench.vcd
$date
	Tue Jun 01 20:39:51 2021
$end
$version
	Icarus Verilog
$end
$timescale
	1ms
$end
$scope module testbench $end
$var wire 1 ! non_blk_b_out $end
$var wire 1 " non_blk_a_out $end
$var wire 1 # blk_b_out $end
$var wire 1 $ blk_a_out $end
$var reg 1 % a_in $end
$var reg 1 & b_in $end
$var reg 1 ' clk $end
$var reg 1 ( rst_n $end
$scope module blk1 $end
$var wire 1 % a_in $end
$var wire 1 $ a_out $end
$var wire 1 & b_in $end
$var wire 1 # b_out $end
$var wire 1 ' clk $end
$var wire 1 ( rst $end
$var reg 1 ) a $end
$var reg 1 * b $end
$upscope $end
$scope module nonblk1 $end
$var wire 1 % a_in $end
$var wire 1 " a_out $end
$var wire 1 & b_in $end
$var wire 1 ! b_out $end
$var wire 1 ' clk $end
$var wire 1 ( rst $end
$var reg 1 + a $end
$var reg 1 , b $end
$upscope $end
$upscope $end
$enddefinitions $end
#0
$dumpvars
x,
x+
x*
x)
x(
x'
x&
x%
x$
x#
x"
x!
$end
#3100
1(
#6100
1!
1,
0"
0+
1#
1*
0$
0)
0'
0(
1&
0%
#6500
1'
#7000
0'
#7500
1'
#8000
0'
#8500
1'
#9000
0'
#9500
1'
#10000
0'
#10500
1(
1'
#11000
0'
#11500
0!
0,
1"
1+
1$
1)
1'
#12000
0'
#12500
1!
1,
0"
0+
1'
#13000
0'
#13500
0!
0,
1"
1+
1'
#14000
0'
#14500
1!
1,
0"
0+
1'
#15000
0'
#15500
0!
0,
1"
1+
1'
#16000
0'
#16500
1!
1,
0"
0+
1'
#17000
0!
0,
1"
1+
0#
0*
0(
0'
0&
1%
#17200
1(
#17500
1!
1,
0"
0+
0$
0)
1'
#18000
0'
#18500
0!
0,
1"
1+
1'
#19000
0'
#19500
1!
1,
0"
0+
1'
#20000
0'
#20500
0!
0,
1"
1+
1'
#21000
0'
#21500
1!
1,
0"
0+
1'
